pyrates/__init__.py
pyrates/pyrates.py
pyrates/pyrates_cli.py
pyrates/pyrates_gui.py
pyrates/data/__init__.py
pyrates/log/__init__.py
pyrates/logger/__init__.py
pyrates/logger/logger.py
pyrates/rate/__init__.py
pyrates/rate/rate.py
pyrates/scraper/__init__.py
pyrates/scraper/scraper.py
pyrates/util/__init__.py
pyrates/util/constants.py
pyrates/util/file_manager.py
pyrates/util/url_manager.py
tests/__init__.py
tests/tests.py
pyrates_cl-0.2.dist-info/LICENSE
pyrates_cl-0.2.dist-info/METADATA
pyrates_cl-0.2.dist-info/WHEEL
pyrates_cl-0.2.dist-info/entry_points.txt
pyrates_cl-0.2.dist-info/top_level.txt
pyrates_cl-0.2.dist-info/RECORD
