Metadata-Version: 2.1
Name: pyrates-cl
Version: 0.2
Summary: Currency Conversion
Home-page: https://github.com/lindeneg/pyrates-cl
Author: Christian Lindeneg
Author-email: christian@lindeneg.org
License: UNKNOWN
Keywords: currency conversion
Platform: UNKNOWN
Classifier: Programming Language :: Python :: 3
Classifier: License :: OSI Approved :: MIT License
Classifier: Operating System :: OS Independent
Requires-Python: >=3.6
Requires-Dist: certifi (>=2019.11.28)
Requires-Dist: chardet (>=3.0.4)
Requires-Dist: idna (>=2.9)
Requires-Dist: lxml (>=4.5.0)
Requires-Dist: mypy (>=0.770)
Requires-Dist: mypy-extensions (>=0.4.3)
Requires-Dist: requests (>=2.23.0)
Requires-Dist: typed-ast (>=1.4.1)
Requires-Dist: typing-extensions (>=3.7.4.1)
Requires-Dist: urllib3 (>=1.25.8)
